README.rst
setup.cfg
setup.py
django_jrac.egg-info/PKG-INFO
django_jrac.egg-info/SOURCES.txt
django_jrac.egg-info/dependency_links.txt
django_jrac.egg-info/not-zip-safe
django_jrac.egg-info/requires.txt
django_jrac.egg-info/top_level.txt
jrac/__init__.py
jrac/models.py
jrac/static/js/jquery.jrac.js
jrac/static/js/jquery.jrac.min.js
jrac/static/js/style.jrac.css
jrac/static/js/images/loading.gif
jrac/static/js/images/viewport_background.gif