Metadata-Version: 1.1
Name: django-jrac
Version: 1.0.2.dev10
Summary: jQuery Resize And Crop (jrac): visually resize an image and place a crop
Home-page: https://github.com/daavve/django-jrac
Author: David McInnis
Author-email: davidm@eagles.ewu.edu
License: GPLv3+
Keywords: django,jquery,jrac
Platform: any
Classifier: Development Status :: 2 - Pre-Alpha
Classifier: Environment :: Web Environment
Classifier: Framework :: Django
Classifier: Intended Audience :: Developers
Classifier: Natural Language :: English
Classifier: License :: OSI Approved :: GNU General Public License v3 or later (GPLv3+)
Classifier: Operating System :: OS Independent
Classifier: Programming Language :: Python :: 3
Classifier: Topic :: Internet :: WWW/HTTP :: Dynamic Content
